README.md
setup.cfg
setup.py
django_rest_framework_google_json_style_api.egg-info/PKG-INFO
django_rest_framework_google_json_style_api.egg-info/SOURCES.txt
django_rest_framework_google_json_style_api.egg-info/dependency_links.txt
django_rest_framework_google_json_style_api.egg-info/requires.txt
django_rest_framework_google_json_style_api.egg-info/top_level.txt
example/__init__.py
example/apps.py
example/conftest.py
example/factories.py
example/models.py
example/serializers.py
example/urls.py
example/urls_test.py
example/views.py
example/migrations/0001_initial.py
example/migrations/__init__.py
example/settings/__init__.py
example/settings/dev.py
example/settings/test.py
example/tests/__init__.py
example/tests/test_pagination.py
example/tests/test_parsers.py
example/tests/test_renderers.py
example/tests/test_views.py
example/tests/utils.py
rest_framework_google_json_style_api/__init__.py
rest_framework_google_json_style_api/pagination.py
rest_framework_google_json_style_api/parsers.py
rest_framework_google_json_style_api/renderers.py
rest_framework_google_json_style_api/settings.py
rest_framework_google_json_style_api/utils.py